fear_and_greed/__init__.py
fear_and_greed/cnn.py
fear_and_greed-0.4.dist-info/LICENSE
fear_and_greed-0.4.dist-info/METADATA
fear_and_greed-0.4.dist-info/WHEEL
fear_and_greed-0.4.dist-info/top_level.txt
fear_and_greed-0.4.dist-info/RECORD
