Metadata-Version: 2.1
Name: fear-and-greed
Version: 0.4
Summary: Python wrapper for CNN Fear & Greed Index.
Home-page: https://github.com/vterron/fear-and-greed
Author: Víctor Terrón
Author-email: quintanar@gmail.com
Project-URL: Bug Tracker, https://github.com/vterron/fear-and-greed/issues
Classifier: Programming Language :: Python :: 3
Classifier: License :: OSI Approved :: MIT License
Classifier: Operating System :: OS Independent
Classifier: Intended Audience :: Financial and Insurance Industry
Requires-Python: >=3.0
License-File: LICENSE
